{
  "main": {
    "id": "535a4508db974cd5",
    "type": "split",
    "children": [
      {
        "id": "f856cd2495e619fc",
        "type": "tabs",
        "children": [
          {
            "id": "7ab72a7243f8eee6",
            "type": "leaf",
            "state": {
              "type": "markdown",
              "state": {
                "file": "app/UseCases/UseCases.md",
                "mode": "source",
                "source": false
              },
              "icon": "lucide-file",
              "title": "UseCases"
            }
          }
        ]
      }
    ],
    "direction": "vertical"
  },
  "left": {
    "id": "38a717c9254eadac",
    "type": "split",
    "children": [
      {
        "id": "e54848eeba5eb9ab",
        "type": "tabs",
        "children": [
          {
            "id": "894421938803867a",
            "type": "leaf",
            "state": {
              "type": "file-explorer",
              "state": {
                "sortOrder": "alphabetical",
                "autoReveal": false
              },
              "icon": "lucide-folder-closed",
              "title": "Files"
            }
          },
          {
            "id": "d38b82c2d522f0c2",
            "type": "leaf",
            "state": {
              "type": "search",
              "state": {
                "query": "",
                "matchingCase": false,
                "explainSearch": false,
                "collapseAll": false,
                "extraContext": false,
                "sortOrder": "alphabetical"
              },
              "icon": "lucide-search",
              "title": "Search"
            }
          },
          {
            "id": "37b063cfd62e47fa",
            "type": "leaf",
            "state": {
              "type": "bookmarks",
              "state": {},
              "icon": "lucide-bookmark",
              "title": "Bookmarks"
            }
          }
        ],
        "currentTab": 1
      }
    ],
    "direction": "horizontal",
    "width": 300
  },
  "right": {
    "id": "f84390238678e90e",
    "type": "split",
    "children": [
      {
        "id": "a4d2dc757e808348",
        "type": "tabs",
        "children": [
          {
            "id": "72b2fe32260422a7",
            "type": "leaf",
            "state": {
              "type": "backlink",
              "state": {
                "collapseAll": false,
                "extraContext": false,
                "sortOrder": "alphabetical",
                "showSearch": false,
                "searchQuery": "",
                "backlinkCollapsed": false,
                "unlinkedCollapsed": true
              },
              "icon": "links-coming-in",
              "title": "Backlinks"
            }
          },
          {
            "id": "5d82af4dc0d6f051",
            "type": "leaf",
            "state": {
              "type": "outgoing-link",
              "state": {
                "linksCollapsed": false,
                "unlinkedCollapsed": true
              },
              "icon": "links-going-out",
              "title": "Outgoing links"
            }
          },
          {
            "id": "6adf4e4a442965d5",
            "type": "leaf",
            "state": {
              "type": "tag",
              "state": {
                "sortOrder": "frequency",
                "useHierarchy": true,
                "showSearch": false,
                "searchQuery": ""
              },
              "icon": "lucide-tags",
              "title": "Tags"
            }
          },
          {
            "id": "39f87d7e3409f2d1",
            "type": "leaf",
            "state": {
              "type": "all-properties",
              "state": {
                "sortOrder": "frequency",
                "showSearch": false,
                "searchQuery": ""
              },
              "icon": "lucide-archive",
              "title": "All properties"
            }
          },
          {
            "id": "3a11389a7b7cd441",
            "type": "leaf",
            "state": {
              "type": "outline",
              "state": {
                "followCursor": false,
                "showSearch": false,
                "searchQuery": ""
              },
              "icon": "lucide-list",
              "title": "Outline"
            }
          }
        ]
      }
    ],
    "direction": "horizontal",
    "width": 300,
    "collapsed": true
  },
  "left-ribbon": {
    "hiddenItems": {
      "switcher:Open quick switcher": false,
      "graph:Open graph view": false,
      "canvas:Create new canvas": false,
      "daily-notes:Open today's daily note": false,
      "templates:Insert template": false,
      "command-palette:Open command palette": false,
      "bases:Create new base": false
    }
  },
  "active": "7ab72a7243f8eee6",
  "lastOpenFiles": [
    "storage/framework/cache/data/ae/77/ae77a22fca64439452b32097ac5fa68408d65869",
    "storage/framework/cache/data/ae/77",
    "storage/framework/cache/data/ae",
    "storage/framework/views/84fbbcf52880882bc54df3ad1811b20e.php",
    "storage/framework/cache/data/56/a5/56a5de895070f4295091e7858efd216709fd375d",
    "storage/framework/cache/data/56/a5",
    "storage/framework/cache/data/56",
    "app/UseCases/Public/Organs/GetOrgansListFilters/GetOrgansListFiltersController.php",
    "app/UseCases/Public/Organs/GetOrgansListFilters",
    "app/UseCases/Public/Organs/GetOrgansList/shared/OrgansFilters.php",
    "app/UseCases/Public/Organs/GetOrgansList/shared",
    "resources/js/src/widgets/table-with-filters/TableWithFilters.md",
    "resources/js/FRONTEND.md",
    "WARP.md",
    "Untitled.canvas",
    "app/BACKEND.md",
    "README.md",
    "app/UseCases/UseCases.md",
    "resources/js/README.md",
    "root.md"
  ]
}